{"type": 1, "language": 0, "style": [{"key": "margin-bottom", "value": "20px"}], "data": [{"block_title": "\u8054\u7edc\u6211\u4eec", "type": 2, "value": "", "style": {"main": {"class": "", "other": ""}, "title": {"class": "title-n", "other": ""}, "content": {"class": "content-n", "other": ""}, "value": {"class": "", "other": ""}}, "title": "\u5982\u679c\u60a8\u6709\u4efb\u4f55\u95ee\u9898\u6216\u9700\u8be6\u7ec6\u8d44\u8baf\uff0c\u6b22\u8fce\u968f\u65f6\u4e0e\u6211\u4eec\u8054\u7edc", "content": [{"type": 2, "style": {"main": {"class": "", "other": ""}, "title": {"class": "title-n gap-n", "other": ""}, "content": {"class": "content-n", "other": "margin: 0px; margin-top: 20px; padding-left: 20px;"}, "value": {"class": "", "other": ""}}, "title": "", "content": [{"type": 1, "style": {"main": {"class": "", "other": ""}, "title": {"class": "text-justify", "other": ""}, "content": {"class": "content-n", "other": "margin: 0px; font-weight: bold;"}, "value": {"class": "", "other": ""}}, "title": "", "content": "\u53f0\u6e7e(\u603b\u516c\u53f8)\u5355\u4e95\u5de5\u4e1a\u80a1\u4efd\u6709\u9650\u516c\u53f8", "value": ""}, {"type": 1, "style": {"main": {"class": "", "other": ""}, "title": {"class": "text-justify", "other": ""}, "content": {"class": "content-n", "other": "margin: 0px; padding-left: 20px;"}, "value": {"class": "", "other": ""}}, "title": "\u5730\u5740\uff1a", "content": "\u65b0\u5317\u5e02\u571f\u57ce\u533a\u4e2d\u5c71\u8def77\u53f7", "value": ""}, {"type": 1, "style": {"main": {"class": "", "other": ""}, "title": {"class": "text-justify", "other": ""}, "content": {"class": "content-n", "other": "margin: 0px; padding-left: 20px;"}, "value": {"class": "", "other": ""}}, "title": "\u7535\u8bdd\uff1a", "content": "+886-2-2268-6191", "value": ""}, {"type": 1, "style": {"main": {"class": "", "other": ""}, "title": {"class": "text-justify", "other": ""}, "content": {"class": "content-n", "other": "margin: 0px; padding-left: 20px;"}, "value": {"class": "", "other": ""}}, "title": "\u4f20\u771f\uff1a", "content": "+886-2-2268-6191", "value": ""}], "value": ""}, {"type": 2, "style": {"main": {"class": "", "other": ""}, "title": {"class": "title-n gap-n", "other": ""}, "content": {"class": "content-n", "other": "margin: 0px; margin-top: 20px; padding-left: 20px;"}, "value": {"class": "", "other": ""}}, "title": "", "content": [{"type": 1, "style": {"main": {"class": "", "other": ""}, "title": {"class": "text-justify", "other": ""}, "content": {"class": "content-n", "other": "margin: 0px; font-weight: bold;"}, "value": {"class": "", "other": ""}}, "title": "", "content": "\u4e2d\u56fd\u6606\u5c71\u5355\u4e95\u5de5\u4e1a(\u6606\u5c71)\u6709\u9650\u516c\u53f8", "value": ""}, {"type": 1, "style": {"main": {"class": "", "other": ""}, "title": {"class": "text-justify", "other": ""}, "content": {"class": "content-n", "other": "margin: 0px; padding-left: 20px;"}, "value": {"class": "", "other": ""}}, "title": "\u5730\u5740\uff1a", "content": "\u6c5f\u82cf\u7701\u82cf\u5dde\u5e02\u6606\u5c71\u5e02\u957f\u5174\u4e1c\u8def266\u53f7", "value": ""}, {"type": 1, "style": {"main": {"class": "", "other": ""}, "title": {"class": "text-justify", "other": ""}, "content": {"class": "content-n", "other": "margin: 0px; padding-left: 20px;"}, "value": {"class": "", "other": ""}}, "title": "\u7535\u8bdd\uff1a", "content": "0512-5766-3780", "value": ""}], "value": ""}, {"type": 2, "style": {"main": {"class": "", "other": ""}, "title": {"class": "title-n gap-n", "other": ""}, "content": {"class": "content-n", "other": "margin: 0px; margin-top: 20px; padding-left: 20px;"}, "value": {"class": "", "other": ""}}, "title": "", "content": [{"type": 1, "style": {"main": {"class": "", "other": ""}, "title": {"class": "text-justify", "other": ""}, "content": {"class": "content-n", "other": "margin: 0px; font-weight: bold;"}, "value": {"class": "", "other": ""}}, "title": "", "content": "\u946b\u661f\u8dc3", "value": ""}, {"type": 1, "style": {"main": {"class": "", "other": ""}, "title": {"class": "text-justify", "other": ""}, "content": {"class": "content-n", "other": "margin: 0px; padding-left: 20px;"}, "value": {"class": "", "other": ""}}, "title": "\u5730\u5740\uff1a", "content": "\u5c71\u4e1c\u6d4e\u5357\u5e02\u69d0\u836b\u533a\u9f50\u5dde\u8def\u9633\u5149\u4fdd\u9669\u5927\u53a618\u697c1809\u5ba4", "value": ""}, {"type": 1, "style": {"main": {"class": "", "other": ""}, "title": {"class": "text-justify", "other": ""}, "content": {"class": "content-n", "other": "margin: 0px; padding-left: 20px;"}, "value": {"class": "", "other": ""}}, "title": "\u7535\u8bdd\uff1a", "content": "0531-55588005", "value": ""}], "value": ""}, {"type": 2, "style": {"main": {"class": "", "other": ""}, "title": {"class": "title-n gap-n", "other": ""}, "content": {"class": "content-n", "other": "margin: 0px; margin-top: 20px; padding-left: 20px;"}, "value": {"class": "", "other": ""}}, "title": "", "content": [{"type": 1, "style": {"main": {"class": "", "other": ""}, "title": {"class": "text-justify", "other": ""}, "content": {"class": "content-n", "other": "margin: 0px; font-weight: bold;"}, "value": {"class": "", "other": ""}}, "title": "", "content": "\u6295\u8d44\u4eba", "value": ""}, {"type": 1, "style": {"main": {"class": "", "other": ""}, "title": {"class": "text-justify", "other": ""}, "content": {"class": "content-n", "other": "margin: 0px; padding-left: 20px;"}, "value": {"class": "", "other": ""}}, "title": "\u4ee3\u7406\u53d1\u8a00\u4eba:", "content": "\u6797\u5c0f\u59d0", "value": ""}, {"type": 1, "style": {"main": {"class": "", "other": ""}, "title": {"class": "text-justify", "other": ""}, "content": {"class": "content-n", "other": "margin: 0px; padding-left: 20px;"}, "value": {"class": "", "other": ""}}, "title": "\u7535\u8bdd\uff1a", "content": "+886 02 2268 6191 EXT 1199", "value": ""}, {"type": 1, "style": {"main": {"class": "", "other": ""}, "title": {"class": "text-justify", "other": ""}, "content": {"class": "content-n", "other": "margin: 0px; padding-left: 20px;"}, "value": {"class": "", "other": ""}}, "title": "\u90ae\u4ef6\u4fe1\u7bb1\uff1a", "content": "IR@singlewell.com.tw", "value": ""}], "value": ""}, {"type": 2, "style": {"main": {"class": "", "other": ""}, "title": {"class": "title-n gap-n", "other": ""}, "content": {"class": "content-n", "other": "margin: 0px; margin-top: 20px; padding-left: 20px;"}, "value": {"class": "", "other": ""}}, "title": "", "content": [{"type": 1, "style": {"main": {"class": "", "other": ""}, "title": {"class": "text-justify", "other": ""}, "content": {"class": "content-n", "other": "margin: 0px; font-weight: bold;"}, "value": {"class": "", "other": ""}}, "title": "", "content": "\u4e1a\u52a1", "value": ""}, {"type": 1, "style": {"main": {"class": "", "other": ""}, "title": {"class": "text-justify", "other": ""}, "content": {"class": "content-n", "other": "margin: 0px; padding-left: 20px;"}, "value": {"class": "", "other": ""}}, "title": "\u8054\u7edc\u4eba:", "content": "\u9ec4\u5c0f\u59d0", "value": ""}, {"type": 1, "style": {"main": {"class": "", "other": ""}, "title": {"class": "text-justify", "other": ""}, "content": {"class": "content-n", "other": "margin: 0px; padding-left: 20px;"}, "value": {"class": "", "other": ""}}, "title": "\u7535\u8bdd\uff1a", "content": "+886 02 2268 6191 EXT 5110", "value": ""}, {"type": 1, "style": {"main": {"class": "", "other": ""}, "title": {"class": "text-justify", "other": ""}, "content": {"class": "content-n", "other": "margin: 0px; padding-left: 20px;"}, "value": {"class": "", "other": ""}}, "title": "\u90ae\u4ef6\u4fe1\u7bb1\uff1a", "content": "customer@singlewell.com.tw", "value": ""}], "value": ""}, {"type": 2, "style": {"main": {"class": "", "other": ""}, "title": {"class": "title-n gap-n", "other": ""}, "content": {"class": "content-n", "other": "margin: 0px; margin-top: 20px; padding-left: 20px;"}, "value": {"class": "", "other": ""}}, "title": "", "content": [{"type": 1, "style": {"main": {"class": "", "other": ""}, "title": {"class": "text-justify", "other": ""}, "content": {"class": "content-n", "other": "margin: 0px; font-weight: bold;"}, "value": {"class": "", "other": ""}}, "title": "", "content": "\u63a1\u8d2d", "value": ""}, {"type": 1, "style": {"main": {"class": "", "other": ""}, "title": {"class": "text-justify", "other": ""}, "content": {"class": "content-n", "other": "margin: 0px; padding-left: 20px;"}, "value": {"class": "", "other": ""}}, "title": "\u8054\u7edc\u4eba:", "content": "\u6d2a\u5c0f\u59d0", "value": ""}, {"type": 1, "style": {"main": {"class": "", "other": ""}, "title": {"class": "text-justify", "other": ""}, "content": {"class": "content-n", "other": "margin: 0px; padding-left: 20px;"}, "value": {"class": "", "other": ""}}, "title": "\u7535\u8bdd\uff1a", "content": "+886 02 2268 6191 EXT 2109", "value": ""}, {"type": 1, "style": {"main": {"class": "", "other": ""}, "title": {"class": "text-justify", "other": ""}, "content": {"class": "content-n", "other": "margin: 0px; padding-left: 20px;"}, "value": {"class": "", "other": ""}}, "title": "\u90ae\u4ef6\u4fe1\u7bb1\uff1a", "content": "supplier@singlewell.com.tw", "value": ""}], "value": ""}, {"type": 2, "style": {"main": {"class": "", "other": ""}, "title": {"class": "title-n gap-n", "other": ""}, "content": {"class": "content-n", "other": "margin: 0px; margin-top: 20px; padding-left: 20px;"}, "value": {"class": "", "other": ""}}, "title": "", "content": [{"type": 1, "style": {"main": {"class": "", "other": ""}, "title": {"class": "text-justify", "other": ""}, "content": {"class": "content-n", "other": "margin: 0px; font-weight: bold;"}, "value": {"class": "", "other": ""}}, "title": "", "content": "\u4eba\u529b\u8d44\u6e90", "value": ""}, {"type": 1, "style": {"main": {"class": "", "other": ""}, "title": {"class": "text-justify", "other": ""}, "content": {"class": "content-n", "other": "margin: 0px; padding-left: 20px;"}, "value": {"class": "", "other": ""}}, "title": "\u8054\u7edc\u4eba:", "content": "\u5deb\u5c0f\u59d0", "value": ""}, {"type": 1, "style": {"main": {"class": "", "other": ""}, "title": {"class": "text-justify", "other": ""}, "content": {"class": "content-n", "other": "margin: 0px; padding-left: 20px;"}, "value": {"class": "", "other": ""}}, "title": "\u7535\u8bdd\uff1a", "content": "+886 02 2268 6191 EXT 1108", "value": ""}, {"type": 1, "style": {"main": {"class": "", "other": ""}, "title": {"class": "text-justify", "other": ""}, "content": {"class": "content-n", "other": "margin: 0px; padding-left: 20px;"}, "value": {"class": "", "other": ""}}, "title": "\u90ae\u4ef6\u4fe1\u7bb1\uff1a", "content": "HR@singlewell.com.tw", "value": ""}], "value": ""}, {"type": 2, "style": {"main": {"class": "", "other": ""}, "title": {"class": "title-n gap-n", "other": ""}, "content": {"class": "content-n", "other": "margin: 0px; margin-top: 20px; padding-left: 20px;"}, "value": {"class": "", "other": ""}}, "title": "", "content": [{"type": 1, "style": {"main": {"class": "", "other": ""}, "title": {"class": "text-justify", "other": ""}, "content": {"class": "content-n", "other": "margin: 0px; font-weight: bold;"}, "value": {"class": "", "other": ""}}, "title": "", "content": "\u4ece\u4e1a\u9053\u5fb7\u4e3e\u62a5", "value": ""}, {"type": 1, "style": {"main": {"class": "", "other": ""}, "title": {"class": "text-justify", "other": ""}, "content": {"class": "content-n", "other": "margin: 0px; padding-left: 20px;"}, "value": {"class": "", "other": ""}}, "title": "\u8054\u7edc\u4eba:", "content": "\u5deb\u5c0f\u59d0", "value": ""}, {"type": 1, "style": {"main": {"class": "", "other": ""}, "title": {"class": "text-justify", "other": ""}, "content": {"class": "content-n", "other": "margin: 0px; padding-left: 20px;"}, "value": {"class": "", "other": ""}}, "title": "\u7535\u8bdd\uff1a", "content": "+886 02 2268 6191 EXT 1108", "value": ""}, {"type": 1, "style": {"main": {"class": "", "other": ""}, "title": {"class": "text-justify", "other": ""}, "content": {"class": "content-n", "other": "margin: 0px; padding-left: 20px;"}, "value": {"class": "", "other": ""}}, "title": "\u90ae\u4ef6\u4fe1\u7bb1\uff1a", "content": "grievance@singlewell.com.tw", "value": ""}], "value": ""}]}]}